LICENSE
MANIFEST.in
README.rst
setup.py
tox.ini
ConfigValidator.egg-info/PKG-INFO
ConfigValidator.egg-info/SOURCES.txt
ConfigValidator.egg-info/dependency_links.txt
ConfigValidator.egg-info/requires.txt
ConfigValidator.egg-info/top_level.txt
configvalidator/__init__.py
configvalidator/features/__init__.py
configvalidator/features/options.py
configvalidator/features/sections.py
configvalidator/tools/__init__.py
configvalidator/tools/basics.py
configvalidator/tools/configValidator.py
configvalidator/tools/exceptions.py
configvalidator/tools/parser.py
configvalidator/tools/result.py
configvalidator/tools/timezone.py
configvalidator/validators/__init__.py
hooks/hook-configvalidator.py
test/codeFormat.py
test/test_cert_validators.py
test/test_config_validator.py
test/test_context_data.py
test/test_custom_option.py
test/test_custom_sections.py
test/test_ecxeptions.py
test/test_invalid_usage.py
test/test_metaclass.py
test/test_parser_obj.py
test/test_port_in_use_validator.py
test/test_result_class.py
test/test_timezone.py
test/test_validators.py
test/testutils/__init__.py
test/testutils/certs/not_before/cert
test/testutils/certs/not_before/key
test/testutils/data/exist/default.ini
test/testutils/data/exist/empty.ini
test/testutils/data/exist/a/.info
test/testutils/data/exist/b/.info
test/testutils/data/exist/c/.info
test/testutils/data/exist/certs/cert_1.crt
test/testutils/data/exist/certs/cert_2.crt
test/testutils/data/exist/certs/cert_3.crt
test/testutils/data/exist/certs/key_1.pem
test/testutils/data/exist/certs/key_2.pem
test/testutils/data/exist/certs/key_2_crypt.pem
test/testutils/data/exist/certs/key_3.pem
test/testutils/data/exist/structure/1/version.json
test/testutils/data/exist/structure/1/log/.info
test/testutils/data/exist/structure/2/not_allowed.file
test/testutils/data/exist/structure/2/version.json
test/testutils/data/exist/structure/2/log/.info
test/testutils/data/exist/structure/3/version.json
test/testutils/data/exist/structure/3/log/.info
test/testutils/data/exist/structure/3/not_allowed_dir/.info
test/testutils/data/exist/structure/4/log/.info
test/testutils/files/utf-16.ini
test/testutils/files/utf-8.ini