Metadata-Version: 1.1
Name: ConfigValidator
Version: 0.2.0
Summary: python module to Validate ini File user input
Home-page: https://github.com/JanHendrikDolling/configvalidator
Author: Jan-Hendrik Dolling
Author-email: UNKNOWN
License: Apache License 2.0
Download-URL: https://github.com/JanHendrikDolling/configvalidator/archive/master.zip
Platform: UNKNOWN
Classifier: Development Status :: 4 - Beta
Classifier: License :: OSI Approved :: Apache Software License
Classifier: Programming Language :: Python
Classifier: Programming Language :: Python :: 2.6
Classifier: Programming Language :: Python :: 2.7
Classifier: Programming Language :: Python :: 3
Classifier: Programming Language :: Python :: 3.3
Classifier: Programming Language :: Python :: 3.4
Classifier: Programming Language :: Python :: 3.5
